bivariate/__init__.py
bivariate/class_component_analysis.py
bivariate/class_copula.py
bivariate/class_dataset.py
bivariate/class_emperical.py
bivariate/class_fitresults.py
bivariate/class_multivar.py
component_reliability/Case_Study_Compontent_Reliability_Tools.py
bivariate-2.0.3.dist-info/LICENSE.txt
bivariate-2.0.3.dist-info/METADATA
bivariate-2.0.3.dist-info/WHEEL
bivariate-2.0.3.dist-info/top_level.txt
bivariate-2.0.3.dist-info/RECORD
