Metadata-Version: 2.1
Name: bivariate
Version: 2.0.3
Summary: This package contains methods that assist in performing bivariate analysis of datasets.
Author: Robert Lanzafame
Author-email: r.lanzafame@tudelft.nl
License: GNU GENERAL PUBLIC LICENSE
Project-URL: Repository, https://github.com/prob-design/bivariate.git
License-File: LICENSE.txt
Requires-Dist: numpy
Requires-Dist: pandas
Requires-Dist: matplotlib >=3.5.0
Requires-Dist: seaborn
Requires-Dist: scipy
Requires-Dist: ipykernel
Requires-Dist: pyvinecopulib
Requires-Dist: scikit-learn
Provides-Extra: test
Requires-Dist: pytest ==7.4.0 ; extra == 'test'
Requires-Dist: pytest-cov >4.0.0 ; extra == 'test'
Requires-Dist: mypy ==1.5.1 ; extra == 'test'
